aioselenium/__init__.py
aioselenium/aioselenium.py
aioselenium/command.py
aioselenium/element.py
aioselenium/keys.py
aioselenium/switch_to.py
aioselenium/test.py
aioselenium-0.0.1.dist-info/LICENSE
aioselenium-0.0.1.dist-info/METADATA
aioselenium-0.0.1.dist-info/WHEEL
aioselenium-0.0.1.dist-info/top_level.txt
aioselenium-0.0.1.dist-info/RECORD
