Metadata-Version: 2.1
Name: aioselenium
Version: 0.0.1
Summary: Very basic asyncio implementation of the Selenium RemoteWebdriver using JSON Wire protocol
Home-page: https://gitlab.com/alexbode/aioselenium
Author: Alex Bode
Author-email: alexvincentbode@gmail.com
License: MIT
Keywords: selenium webdriver asyncio aiohttp remote
Platform: UNKNOWN
Requires-Dist: aiohttp
